ddsketch/__init__.py
ddsketch/__version.py
ddsketch/_version.py
ddsketch/ddsketch.py
ddsketch/mapping.py
ddsketch/py.typed
ddsketch/store.py
ddsketch/pb/__init__.py
ddsketch/pb/ddsketch_pb2.py
ddsketch/pb/ddsketch_pre319_pb2.py
ddsketch/pb/proto.py
ddsketch-2.0.4.dist-info/LICENSE
ddsketch-2.0.4.dist-info/LICENSE-3rdparty.csv
ddsketch-2.0.4.dist-info/METADATA
ddsketch-2.0.4.dist-info/NOTICE
ddsketch-2.0.4.dist-info/WHEEL
ddsketch-2.0.4.dist-info/top_level.txt
ddsketch-2.0.4.dist-info/RECORD
