Metadata-Version: 2.1
Name: ddsketch
Version: 2.0.4
Summary: Distributed quantile sketches
Home-page: http://github.com/datadog/sketches-py
Author: Jee Rim, Charles-Philippe Masson, Homin Lee
Author-email: jee.rim@datadoghq.com, charles.masson@datadoghq.com, homin@datadoghq.com
License: UNKNOWN
Download-URL: https://github.com/DataDog/sketches-py/archive/v1.0.tar.gz
Keywords: ddsketch,quantile,sketch
Platform: UNKNOWN
Classifier: Programming Language :: Python :: 3
Classifier: License :: OSI Approved :: Apache Software License
Requires-Python: >=2.7
License-File: LICENSE
License-File: LICENSE-3rdparty.csv
License-File: NOTICE
